reverse_string/__init__.py
reverse_string/reverse.py
reverse_string003/__init__.py
reverse_string003/reverse.py
my_reverse_string-0.1.1.dist-info/METADATA
my_reverse_string-0.1.1.dist-info/WHEEL
my_reverse_string-0.1.1.dist-info/top_level.txt
my_reverse_string-0.1.1.dist-info/RECORD
